[
    { "id": 1, "name": "Katholische Kirche St. Maria (LU)", "lat": 47.08177, "lon": 8.34028 },
    { "id": 2, "name": "Hofkirche St. Leodegar (LU)", "lat": 47.0553, "lon": 8.3119 },
    { "id": 3, "name": "Peterskapelle (LU)", "lat": 47.0519, "lon": 8.3071 },
    { "id": 4, "name": "Christuskirche (LU)", "lat": 47.0479, "lon": 8.3084 },
    { "id": 5, "name": "Kapelle St. Niklausen, Willisau (LU)", "lat": 47.1210, "lon": 7.9906 },
    { "id": 6, "name": "Kirche St. Theodul, Littau (LU)", "lat": 47.0645, "lon": 8.2606 },
    { "id": 7, "name": "Reformierte Lukaskirche (LU)", "lat": 47.0495, "lon": 8.3104 },
    { "id": 8, "name": "Kirche St. Pankratius, Hitzkirch (LU)", "lat": 47.2268, "lon": 8.2660 },
    { "id": 9, "name": "Kirche St. Peter und Paul, Willisau (LU)", "lat": 47.1217, "lon": 7.9900 },
    { "id": 10, "name": "Pfarrkirche St. Oswald (ZU)", "lat": 47.1667, "lon": 8.5167 },
    { "id": 11, "name": "Reformierte Kirche Zug (ZU)", "lat": 47.1725, "lon": 8.5175 },
    { "id": 12, "name": "Pfarrkirche St. Martin, Baar (ZU)", "lat": 47.1950, "lon": 8.5280 },
    { "id": 13, "name": "Pfarrkirche St. Jakob, Cham (ZU)", "lat": 47.1820, "lon": 8.4630 },
    { "id": 14, "name": "Pfarrkirche St. Johannes, Oberägeri (ZU)", "lat": 47.1350, "lon": 8.6100 },
    { "id": 15, "name": "Pfarrkirche St. Wendelin, Unterägeri (ZU)", "lat": 47.1370, "lon": 8.5830 },
    { "id": 16, "name": "Pfarrkirche St. Wolfgang, Hünenberg (ZU)", "lat": 47.1750, "lon": 8.4250 },
    { "id": 17, "name": "Pfarrkirche St. Verena, Risch (ZU)", "lat": 47.1330, "lon": 8.4500 },
    { "id": 18, "name": "Pfarrkirche St. German, Steinhausen (ZU)", "lat": 47.1950, "lon": 8.4850 },
    { "id": 19, "name": "Pfarrkirche St. Matthias, Walchwil (ZU)", "lat": 47.1000, "lon": 8.5200 },   
    { "id": 20, "name": "Grossmünster (ZH)", "lat": 47.3709, "lon": 8.5446 },
    { "id": 21, "name": "Fraumünster (ZH)", "lat": 47.3699, "lon": 8.5417 },
    { "id": 22, "name": "St. Peter Kirche (ZH)", "lat": 47.3710, "lon": 8.5403 },
    { "id": 23, "name": "Predigerkirche (ZH)", "lat": 47.3733, "lon": 8.5450 },
    { "id": 24, "name": "Liebfrauenkirche (ZH)", "lat": 47.3793, "lon": 8.5435 },
    { "id": 25, "name": "Kirche Enge (ZH)", "lat": 47.3640, "lon": 8.5320 },
    { "id": 26, "name": "Kirche Fluntern (ZH)", "lat": 47.3775, "lon": 8.5630 },
    { "id": 27, "name": "Kirche Neumünster (ZH)", "lat": 47.3550, "lon": 8.5610 },
    { "id": 28, "name": "Kirche St. Jakob (ZH)", "lat": 47.3780, "lon": 8.5250 },
    { "id": 29, "name": "Kirche St. Anton (ZH)", "lat": 47.3880, "lon": 8.5360 },   
    { "id": 30, "name": "Pfarrkirche St. Peter und Paul, Sarnen (OW)", "lat": 46.8961, "lon": 8.2463 },
    { "id": 31, "name": "Pfarrkirche St. Gallus, Kerns (OW)", "lat": 46.9025, "lon": 8.2750 },
    { "id": 32, "name": "Pfarrkirche St. Theodul, Sachseln (OW)", "lat": 46.8694, "lon": 8.2397 },
    { "id": 33, "name": "Pfarrkirche St. Maria, Alpnach (OW)", "lat": 46.9400, "lon": 8.2722 },
    { "id": 34, "name": "Pfarrkirche St. Laurentius, Giswil (OW)", "lat": 46.8333, "lon": 8.1833 },
    { "id": 35, "name": "Pfarrkirche St. Nikolaus, Lungern (OW)", "lat": 46.7850, "lon": 8.1597 },
    { "id": 36, "name": "Klosterkirche Engelberg (OW)", "lat": 46.8214, "lon": 8.4083 },
    { "id": 37, "name": "Pfarrkirche St. Peter und Paul, Stans (NW)", "lat": 46.9586, "lon": 8.3664 },
    { "id": 38, "name": "Pfarrkirche St. Heinrich, Ennetmoos (NW)", "lat": 46.9417, "lon": 8.3244 },
    { "id": 39, "name": "Pfarrkirche St. Martin, Buochs (NW)", "lat": 46.9744, "lon": 8.4222 },
    { "id": 40, "name": "Pfarrkirche St. Theodul, Ennetbürgen (NW)", "lat": 46.9847, "lon": 8.4125 },
    { "id": 41, "name": "Pfarrkirche St. Gallus, Oberdorf (NW)", "lat": 46.9572, "lon": 8.3861 },
    { "id": 42, "name": "Pfarrkirche St. Marzellus, Wolfenschiessen (NW)", "lat": 46.9075, "lon": 8.3933 },
    { "id": 43, "name": "Pfarrkirche St. Nikolaus, Hergiswil (NW)", "lat": 46.9833, "lon": 8.3083 },
    { "id": 44, "name": "Pfarrkirche St. Antonius, Emmetten (NW)", "lat": 46.9575, "lon": 8.5111 },
    { "id": 45, "name": "Pfarrkirche St. Jost, Dallenwil (NW)", "lat": 46.9333, "lon": 8.3875 },
    { "id": 46, "name": "Pfarrkirche St. Maria, Beckenried (NW)", "lat": 46.9647, "lon": 8.4722 },
    { "id": 47, "name": "Pfarrkirche St. Martin, Schwyz (SZ)", "lat": 47.0200, "lon": 8.6520 },
    { "id": 48, "name": "Pfarrkirche St. Peter und Paul, Küssnacht am Rigi (SZ)", "lat": 47.0830, "lon": 8.4410 },
    { "id": 49, "name": "Pfarrkirche St. Marzellus, Gersau (SZ)", "lat": 46.9900, "lon": 8.5260 },
    { "id": 50, "name": "Pfarrkirche St. Gallus, Lachen (SZ)", "lat": 47.1910, "lon": 8.8520 },
    { "id": 51, "name": "Pfarrkirche St. Jakob, Einsiedeln (SZ)", "lat": 47.1280, "lon": 8.7500 },
    { "id": 52, "name": "Pfarrkirche St. Anna, Goldau (SZ)", "lat": 47.0480, "lon": 8.5500 },
    { "id": 53, "name": "Pfarrkirche St. Laurentius, Wollerau (SZ)", "lat": 47.1950, "lon": 8.7190 },
    { "id": 54, "name": "Pfarrkirche St. Verena, Schindellegi (SZ)", "lat": 47.1740, "lon": 8.7100 },
    { "id": 56, "name": "Pfarrkirche St. Josef, Brunnen (SZ)", "lat": 46.9950, "lon": 8.6070 },
    { "id": 57, "name": "Pfarrkirche St. Nikolaus, Arth (SZ)", "lat": 47.0620, "lon": 8.5260 }




]